nano_wait_vision/__init__.py
nano_wait_vision/ocr.py
nano_wait_vision/screen.py
nano_wait_vision/vision.py
nano_wait_vision/vision_state.py
nano_wait_vision-0.2.0.dist-info/licenses/LICENSE
nano_wait_vision-0.2.0.dist-info/METADATA
nano_wait_vision-0.2.0.dist-info/WHEEL
nano_wait_vision-0.2.0.dist-info/top_level.txt
nano_wait_vision-0.2.0.dist-info/RECORD
