Metadata-Version: 2.4
Name: nano-wait-vision
Version: 0.2.0
Summary: Vision extension for nano-wait automation
Author: Luiz Seabra De Marco
License: MIT
Project-URL: Repository, https://github.com/LuizSeabraDeMarco/NanoWaitVision
Classifier: Programming Language :: Python :: 3
Classifier: License :: OSI Approved :: MIT License
Classifier: Operating System :: OS Independent
Requires-Python: >=3.9
License-File: LICENSE
Requires-Dist: nano-wait
Requires-Dist: opencv-python
Requires-Dist: pytesseract
Requires-Dist: pyautogui
Requires-Dist: numpy
Dynamic: license-file
